[
        {
            "name": "ภูเก็ต"
        },
        {
            "name": "พังงา"
        },
        {
            "name": "เชียงใหม่"
        },
        {
            "name": "ขอนแก่น"
        },
        {
            "name": "อุดรธานี"
        },
        {
            "name": "สุโขทัย"
        },
        {
            "name": "ประจวบคีรีขันธ์"
        },
        {
            "name": "เลย"
        },
        {
            "name": "ปทุมธานี"
        },
        {
            "name": "สมุทรปราการ"
        },
        {
            "name": "สมุทรสงคราม"
        },
        {
            "name": "ตาก"
        },
        {
            "name": "ยะลา"
        },
        {
            "name": "สงขลา"
        },
        {
            "name": "ราชบุรี"
        }
    ]